aligned_text_table/__init__.py
aligned_text_table/parser.py
aligned_text_table-0.3.0.dist-info/METADATA
aligned_text_table-0.3.0.dist-info/WHEEL
aligned_text_table-0.3.0.dist-info/RECORD
