Metadata-Version: 2.1
Name: aligned-text-table
Version: 0.3.0
Summary: Parser for space-aligned tables in plain text
Home-page: https://github.com/nottrobin/aligned-text-table
License: Public domain
Author: Robin Winslow
Author-email: robin@robinwinslow.co.uk
Requires-Python: >=3.10,<4.0
Classifier: License :: Other/Proprietary License
Classifier: Programming Language :: Python :: 3
Classifier: Programming Language :: Python :: 3.10
Classifier: Programming Language :: Python :: 3.11
Project-URL: Repository, https://github.com/nottrobin/aligned-text-table
